README.md
setup.py
sql_annotation/__init__.py
sql_annotation/annotation.py
sql_annotation/conn.py
sql_annotation/database.py
sql_annotation/error.py
sql_annotation/logger.py
sql_annotation.egg-info/PKG-INFO
sql_annotation.egg-info/SOURCES.txt
sql_annotation.egg-info/dependency_links.txt
sql_annotation.egg-info/requires.txt
sql_annotation.egg-info/top_level.txt