Metadata-Version: 1.0
Name: sql-annotation
Version: 1.0.0
Summary: Database Annotation, author liyuanjun
Home-page: https://github.com/tomoncle/sql-annotation
Author: liyuanjun
Author-email: 1123431949@qq.com
License: MIT
Platform: UNKNOWN
